PyDANSAT/__init__.py
PyDANSAT/curvenumber.py
PyDANSAT/greenampt.py
PyDANSAT-0.0.1.dist-info/LICENSE.txt
PyDANSAT-0.0.1.dist-info/METADATA
PyDANSAT-0.0.1.dist-info/WHEEL
PyDANSAT-0.0.1.dist-info/top_level.txt
PyDANSAT-0.0.1.dist-info/RECORD
