Metadata-Version: 2.1
Name: PyDANSAT
Version: 0.0.1
Summary: Watershed modeling platform
Home-page: https://github.com/IWMI-KR/PyDANSAT
Author: Jaepil Cho
Author-email: jpcho89@gmail.com
License: UNKNOWN
Platform: UNKNOWN
Classifier: Programming Language :: Python :: 3
Classifier: License :: OSI Approved :: MIT License
Classifier: Operating System :: OS Independent
Requires-Python: >=3.6
